<?xml version="1.0" encoding="UTF-8"?>
<manifest>
   <ParagraphStyleRange AppliedParagraphStyle="ParagraphStyle/.Chap .Back .App .Lab">
      <CharacterStyleRange AppliedCharacterStyle="CharacterStyle/$ID/[No character style]">
         <Content>Appendix B</Content>
      </CharacterStyleRange>
   </ParagraphStyleRange>
   <ParagraphStyleRange AppliedParagraphStyle="ParagraphStyle/.Chap .Back .App .Lab">
      <CharacterStyleRange AppliedCharacterStyle="CharacterStyle/$ID/[No character style]">
         <Br/>
      </CharacterStyleRange>
   </ParagraphStyleRange>
   <ParagraphStyleRange AppliedParagraphStyle="ParagraphStyle/.Chap .Back Sec .Title">
      <CharacterStyleRange AppliedCharacterStyle="CharacterStyle/$ID/[No character style]">
         <Content>NCCER Credentials</Content>
      </CharacterStyleRange>
   </ParagraphStyleRange>
   <ParagraphStyleRange AppliedParagraphStyle="ParagraphStyle/.Chap .Back Sec .Title">
      <CharacterStyleRange AppliedCharacterStyle="CharacterStyle/$ID/[No character style]">
         <Br/>
      </CharacterStyleRange>
   </ParagraphStyleRange>
   <Rectangle Self="d57e14">
      <Properties>
         <PathGeometry>
            <GeometryPathType PathOpen="false">
               <PathPointArray>
                  <PathPointType Anchor="0 0" LeftDirection="0 0" RightDirection="0 0"/>
                  <PathPointType Anchor="0 100" LeftDirection="0 100" RightDirection="0 100"/>
                  <PathPointType Anchor="504 100" LeftDirection="504 100" RightDirection="504 100"/>
                  <PathPointType Anchor="504 0" LeftDirection="504 0" RightDirection="504 0"/>
               </PathPointArray>
            </GeometryPathType>
         </PathGeometry>
      </Properties>
      <FrameFittingOption AutoFit="true" LeftCrop="0" TopCrop="0" RightCrop="0" BottomCrop="0"
                          FittingOnEmptyFrame="Proportionally"
                          FittingAlignment="CenterAnchor"/>
      <Image ImageRenderingIntent="UseColorSettings"
             AppliedObjectStyle="ObjectStyle/$ID/[None]"
             Visible="true"
             Name="$ID/"
             Self="rc_d57e14Image">
         <Link Self="d57e14Link" AssetURL="$ID/" AssetID="$ID/"
               LinkResourceURI="file:/Users/gpage/Documents/Content/ncs_content/9780130210100/temp/ncs2IDML/graphics/print/02101-18_A01.eps"/>
      </Image>
   </Rectangle>
   <Rectangle Self="d57e17">
      <Properties>
         <PathGeometry>
            <GeometryPathType PathOpen="false">
               <PathPointArray>
                  <PathPointType Anchor="0 0" LeftDirection="0 0" RightDirection="0 0"/>
                  <PathPointType Anchor="0 100" LeftDirection="0 100" RightDirection="0 100"/>
                  <PathPointType Anchor="504 100" LeftDirection="504 100" RightDirection="504 100"/>
                  <PathPointType Anchor="504 0" LeftDirection="504 0" RightDirection="504 0"/>
               </PathPointArray>
            </GeometryPathType>
         </PathGeometry>
      </Properties>
      <FrameFittingOption AutoFit="true" LeftCrop="0" TopCrop="0" RightCrop="0" BottomCrop="0"
                          FittingOnEmptyFrame="Proportionally"
                          FittingAlignment="CenterAnchor"/>
      <Image ImageRenderingIntent="UseColorSettings"
             AppliedObjectStyle="ObjectStyle/$ID/[None]"
             Visible="true"
             Name="$ID/"
             Self="rc_d57e17Image">
         <Link Self="d57e17Link" AssetURL="$ID/" AssetID="$ID/"
               LinkResourceURI="file:/Users/gpage/Documents/Content/ncs_content/9780130210100/temp/ncs2IDML/graphics/print/02101-18_A02.eps"/>
      </Image>
   </Rectangle>
   <Rectangle Self="d57e20">
      <Properties>
         <PathGeometry>
            <GeometryPathType PathOpen="false">
               <PathPointArray>
                  <PathPointType Anchor="0 0" LeftDirection="0 0" RightDirection="0 0"/>
                  <PathPointType Anchor="0 100" LeftDirection="0 100" RightDirection="0 100"/>
                  <PathPointType Anchor="504 100" LeftDirection="504 100" RightDirection="504 100"/>
                  <PathPointType Anchor="504 0" LeftDirection="504 0" RightDirection="504 0"/>
               </PathPointArray>
            </GeometryPathType>
         </PathGeometry>
      </Properties>
      <FrameFittingOption AutoFit="true" LeftCrop="0" TopCrop="0" RightCrop="0" BottomCrop="0"
                          FittingOnEmptyFrame="Proportionally"
                          FittingAlignment="CenterAnchor"/>
      <Image ImageRenderingIntent="UseColorSettings"
             AppliedObjectStyle="ObjectStyle/$ID/[None]"
             Visible="true"
             Name="$ID/"
             Self="rc_d57e20Image">
         <Link Self="d57e20Link" AssetURL="$ID/" AssetID="$ID/"
               LinkResourceURI="file:/Users/gpage/Documents/Content/ncs_content/9780130210100/temp/ncs2IDML/graphics/print/02101-18_A03.eps"/>
      </Image>
   </Rectangle>
</manifest>